speechtotext/__init__.py
speechtotext/__main__.py
speechtotext/messaging.py
speechtotext/speechtext.py
speechtotext-0.0.3.dist-info/DESCRIPTION.rst
speechtotext-0.0.3.dist-info/METADATA
speechtotext-0.0.3.dist-info/RECORD
speechtotext-0.0.3.dist-info/WHEEL
speechtotext-0.0.3.dist-info/entry_points.txt
speechtotext-0.0.3.dist-info/metadata.json
speechtotext-0.0.3.dist-info/top_level.txt
