Metadata-Version: 2.0
Name: speechtotext
Version: 0.0.3
Summary: Text to Speech for python
Home-page: https://github.com/benhoff/speechtotext
Author: Ben Hoff
Author-email: beohoff@gmail.com
License: GPL3
Keywords: sound capture to text
Platform: UNKNOWN
Classifier: Development Status :: 1 - Planning
Classifier: Intended Audience :: Developers
Classifier: License :: OSI Approved :: GNU General Public License v3 (GPLv3)
Classifier: Programming Language :: Python :: 3
Classifier: Programming Language :: Python :: 3.5
Classifier: Topic :: Multimedia :: Sound/Audio :: Capture/Recording
Classifier: Topic :: Utilities
Classifier: Operating System :: OS Independent
Requires-Dist: PyAudio
Requires-Dist: SpeechRecognition
Requires-Dist: pluginmanager
Requires-Dist: pyzmq
Requires-Dist: vexmessage
Provides-Extra: dev
Requires-Dist: flake8; extra == 'dev'
